astraSDK.py
netapp_astra_toolkits-2.0.data/data/config/config.yaml
netapp_astra_toolkits-2.0.data/scripts/toolkit.py
netapp_astra_toolkits-2.0.dist-info/LICENSE
netapp_astra_toolkits-2.0.dist-info/METADATA
netapp_astra_toolkits-2.0.dist-info/WHEEL
netapp_astra_toolkits-2.0.dist-info/top_level.txt
netapp_astra_toolkits-2.0.dist-info/RECORD
