Metadata-Version: 2.1
Name: netapp-astra-toolkits
Version: 2.0
Summary: Toolkit and SDK for interacting with Astra
Home-page: https://github.com/NetApp/netapp-astra-toolkits
Author: Josh Paetzel
Author-email: Josh.Paetzel@netapp.com
License: UNKNOWN
Platform: UNKNOWN
Classifier: Programming Language :: Python :: 3
Classifier: License :: OSI Approved :: Apache Software License
Classifier: Operating System :: OS Independent
License-File: LICENSE
